sqlrag/__init__.py
sqlrag/cache.py
sqlrag/constants.py
sqlrag/exceptions.py
sqlrag/open_llm.py
sqlrag/open_sql_rag.py
sqlrag/utils.py
sqlrag-0.1.dev43.dist-info/LICENSE.md
sqlrag-0.1.dev43.dist-info/METADATA
sqlrag-0.1.dev43.dist-info/WHEEL
sqlrag-0.1.dev43.dist-info/top_level.txt
sqlrag-0.1.dev43.dist-info/RECORD
