Metadata-Version: 2.1
Name: sqlrag
Version: 0.1.dev43
Summary: An open-source Generative AI (GenAI) application designed to provide users
Author: Mindfire Digital LLP
Author-email: abdulla.ansari@mindfiresolutions.com
Classifier: Programming Language :: Python :: 3
Classifier: License :: OSI Approved :: MIT License
Classifier: Operating System :: OS Independent
Requires-Python: >=3.10
License-File: LICENSE.md
Requires-Dist: langchain
Requires-Dist: langchain-experimental
Requires-Dist: langchain-openai
Requires-Dist: langchain-community
Requires-Dist: redis
Requires-Dist: gpt4all
